{
    "data": {
        "nationality": "Indonesian",
        "edu_s1": {
            "major": "Agronomy",
            "university": "Bogor Agricultural Institute",
            "country": "Indonesia"
        },
        "edu_s2": null,
        "edu_s3": null,
        "edu_profesi": null,
        "edu_vokasi": null,
        "work_experience": [
            {
                "position": "Director of Human Resources, CREM and Company Marketing",
                "company": "PT Adira Dinamika Multi Finance Tbk",
                "country": "Indonesia",
                "start_year": 2017,
                "end_year": null
            },
            {
                "position": "Director of the Company's Human Resources",
                "company": "PT Adira Dinamika Multi Finance Tbk",
                "country": "Indonesia",
                "start_year": 2013,
                "end_year": 2017
            },
            {
                "position": "Deputy Director of Human Resources and General Affairs",
                "company": "PT Adira Dinamika Multi Finance Tbk",
                "country": "Indonesia",
                "start_year": 2010,
                "end_year": 2013
            },
            {
                "position": "Head of Human Resources and General Affairs Division",
                "company": "PT Adira Dinamika Multi Finance Tbk",
                "country": "Indonesia",
                "start_year": 2003,
                "end_year": 2010
            },
            {
                "position": "Head of the Company's Remuneration and Human Resources Development Department",
                "company": "PT Adira Dinamika Multi Finance Tbk",
                "country": "Indonesia",
                "start_year": 2002,
                "end_year": 2003
            },
            {
                "position": "Remuneration Senior Analyst",
                "company": "PT Sumalindo Lestari Jaya Tbk (Group PT Astra International Tbk)",
                "country": "Indonesia",
                "start_year": 2000,
                "end_year": 2002
            }
        ],
        "name": "Swandajani Gunadi",
        "position": "Director",
        "company": "ID_ADMF_IR_2023"
    },
    "sources": [
        65,
        104,
        264,
        143,
        113,
        63
    ]
}