{
    "data": {
        "name": "James Dimon",
        "position": "Chairman and Chief Executive Officer",
        "start_tenure": "2005-12-31",
        "end_tenure": null,
        "gender": "Male",
        "birthdate_or_age": "1956-03-13",
        "nationality": "American",
        "education_bachelor": {
            "major": "Psychology",
            "university": "Tufts University",
            "country": "USA"
        },
        "education_master": {
            "major": "Business Administration",
            "university": "Harvard University",
            "country": "USA"
        },
        "education_doctoral": {
            "major": null,
            "university": null,
            "country": null
        },
        "working_experience": [
            {
                "position": "Chief Executive Officer",
                "company": "JPMorgan Chase & Co.",
                "country": "USA",
                "start_date": "2005-12-31",
                "end_date": null
            },
            {
                "position": "President and Chief Operating Officer",
                "company": "JPMorgan Chase & Co.",
                "country": "USA",
                "start_date": "2004-01-01",
                "end_date": "2005-12-30"
            },
            {
                "position": "CEO",
                "company": "Bank One Corporation",
                "country": "USA",
                "start_date": "2000-01-01",
                "end_date": "2004-01-01"
            },
            {
                "position": "President",
                "company": "Citigroup",
                "country": "USA",
                "start_date": "1998-01-01",
                "end_date": "2000-01-01"
            },
            {
                "position": "Chief Financial Officer",
                "company": "American Express",
                "country": "USA",
                "start_date": "1990-01-01",
                "end_date": "1998-01-01"
            }
        ],
        "company": "US_JPM_AR_2023"
    },
    "sources": [
        360,
        361,
        69,
        200
    ]
}